{
  "lord": {
    "StrengthMultiplier": 1.5,
    "DotCount": 5,
    "DotColour": "Blue",
    "Type": "Europ"
  },
  "startTroops": {
    "normal": {
      "EuropArcher": 10,
      "Crossbowman": 8,
      "Pikeman": 5

    },
    "crusader": {
      "EuropArcher": 20,
      "Crossbowman": 15,
      "Pikeman": 25,
      "Maceman": 25,
      "Spearman": 70
    },
    "deathmatch": {
      "EuropArcher": 10,
      "Crossbowman": 8,
      "Pikeman": 5
    }
  },
  "aic": {
    "WallDecoration": 12,
	"Unknown001": 0,
	"Unknown002": 0,
	"Unknown003": 0,
	"Unknown004": 0,
	"Unknown005": 0,
	"CriticalPopularity": 6500,
	"LowestPopularity": 9700,
	"HighestPopularity": 9900,
	"TaxesMin": 3,
	"TaxesMax": 11,
	"Unknown011": 20,
	"Farm1": "DairyFarm",
	"Farm2": "WheatFarm",
	"Farm3": "HopFarm",
	"Farm4": "DairyFarm",
	"Farm5": "WheatFarm",
	"Farm6": "DairyFarm",
	"Farm7": "WheatFarm",
	"Farm8": "HopFarm",
	"PopulationPerFarm": 1,
	"PopulationPerWoodcutter": 1,
	"PopulationPerQuarry": 1,
	"PopulationPerIronmine": 1,
	"PopulationPerPitchrig": 1,
	"MaxQuarries": 3,
	"MaxIronmines": 9,
	"MaxWoodcutters": 5,
	"MaxPitchrigs": 2,
	"MaxFarms": 12,
	"BuildInterval": 1,
	"ResourceRebuildDelay": 50,
	"MaxFood": 800,
	"MinimumApples": 10,
	"MinimumCheese": 10,
	"MinimumBread": 10,
	"MinimumWheat": -1,
	"MinimumHop": 5,
	"TradeAmountFood": 5,
	"TradeAmountEquipment": 4,
	"Unknown040": 30,
	"MinimumGoodsRequiredAfterTrade": 15,
	"DoubleRationsFoodThreshold": 60,
	"MaxWood": 70,
	"MaxStone": 40,
	"MaxResourceOther": 10,
	"MaxEquipment": 10,
	"MaxBeer": 8,
	"MaxResourceVariance": 5,
	"RecruitGoldThreshold": 200,
	"BlacksmithSetting": "Maces",
	"FletcherSetting": "Both",
	"PoleturnerSetting": "Both",
	"SellResource01": "None",
	"SellResource02": "None",
	"SellResource03": "None",
	"SellResource04": "None",
	"SellResource05": "None",
	"SellResource06": "None",
	"SellResource07": "None",
	"SellResource08": "None",
	"SellResource09": "None",
	"SellResource10": "None",
	"SellResource11": "None",
	"SellResource12": "None",
	"SellResource13": "Swords",
	"SellResource14": "None",
	"SellResource15": "None",
	"DefWallPatrolRallyTime": 10,
	"DefWallPatrolGroups": 4,
	"DefSiegeEngineGoldThreshold": 100,
	"DefSiegeEngineBuildDelay": 20,
	"Unknown072": 200,
	"Unknown073": 40,
	"RecruitProbDefDefault": 70,
	"RecruitProbDefWeak": 100,
	"RecruitProbDefStrong": 10,
	"RecruitProbRaidDefault": 10,
	"RecruitProbRaidWeak": 0,
	"RecruitProbRaidStrong": 10,
	"RecruitProbAttackDefault": 20,
	"RecruitProbAttackWeak": 0,
	"RecruitProbAttackStrong": 80,
	"SortieUnitRangedMin": 6,
	"SortieUnitRanged": "Crossbowman",
	"SortieUnitMeleeMin": 5,
	"SortieUnitMelee": "Maceman",
	"DefDiggingUnitMax": 0,
	"DefDiggingUnit": "Spearman",
	"RecruitInterval": 0,
	"RecruitIntervalWeak": 0,
	"RecruitIntervalStrong": 0,
	"DefTotal": 140,
	"OuterPatrolGroupsCount": 4,
	"OuterPatrolGroupsMove": "True",
	"OuterPatrolRallyDelay": 20,
	"DefWalls": 110,
	"DefUnit1": "Crossbowman",
	"DefUnit2": "EuropArcher",
	"DefUnit3": "Crossbowman",
	"DefUnit4": "EuropArcher",
	"DefUnit5": "Pikeman",
	"DefUnit6": "None",
	"DefUnit7": "None",
	"DefUnit8": "None",
	"RaidUnitsBase": 10,
	"RaidUnitsRandom": 5,
	"RaidUnit1": "Maceman",
	"RaidUnit2": "Spearman",
	"RaidUnit3": "EuropArcher",
	"RaidUnit4": "None",
	"RaidUnit5": "None",
	"RaidUnit6": "None",
	"RaidUnit7": "None",
	"RaidUnit8": "None",
	"HarassingSiegeEngine1": "Catapult",
	"HarassingSiegeEngine2": "None",
	"HarassingSiegeEngine3": "None",
	"HarassingSiegeEngine4": "None",
	"HarassingSiegeEngine5": "None",
	"HarassingSiegeEngine6": "None",
	"HarassingSiegeEngine7": "None",
	"HarassingSiegeEngine8": "None",
	"HarassingSiegeEnginesMax": 2,
	"Unknown124": 0,
	"AttForceBase": 520,
	"AttForceRandom": 50,
	"AttForceSupportAllyThreshold": 120,
	"AttForceRallyPercentage": 50,
	"Unknown129": 100,
	"Unknown130": 0,
	"AttUnitPatrolRecommandDelay": 5,
	"Unknown132": 0,
	"SiegeEngine1": "Catapult",
	"SiegeEngine2": "Catapult",
	"SiegeEngine3": "Trebuchet",
	"SiegeEngine4": "BatteringRam",
	"SiegeEngine5": "Trebuchet",
	"SiegeEngine6": "Catapult",
	"SiegeEngine7": "BatteringRam",
	"SiegeEngine8": "Catapult",
	"CowThrowInterval": 26,
	"Unknown142": 0,
	"AttMaxEngineers": 40,
	"AttDiggingUnit": "Spearman",
	"AttDiggingUnitMax": 120,
	"AttUnit2": "Crossbowman",
	"AttUnit2Max": 160,
	"AttMaxAssassins": 0,
	"AttMaxLaddermen": 80,
	"AttMaxTunnelers": 12,
	"AttUnitPatrol": "None",
	"AttUnitPatrolMax": 0,
	"AttUnitPatrolGroupsCount": 3,
	"AttUnitBackup": "EuropArcher",
	"AttUnitBackupMax": 50,
	"AttUnitBackupGroupsCount": 1,
	"AttUnitEngage": "None",
	"AttUnitEngageMax": 0,
	"AttUnitSiegeDef": "None",
	"AttUnitSiegeDefMax": 0,
	"AttUnitSiegeDefGroupsCount": 0,
	"AttUnitMain1": "Spearman",
	"AttUnitMain2": "Maceman",
	"AttUnitMain3": "Pikeman",
	"AttUnitMain4": "Maceman",
	"AttMaxDefault": 400,
	"AttMainGroupsCount": 1,
	"TargetChoice": "Closest"
  }
}